customerService/__init__.py
customerService/auth.py
customerService/base.py
customerService/constants.py
customerService/datasets.py
customerService/demo.py
customerService/env.py
customerService/inspection.py
customerService/order.py
customerService/page_params.py
customerService/upload.py
datatang_customer_service-1.0.3.dist-info/METADATA
datatang_customer_service-1.0.3.dist-info/WHEEL
datatang_customer_service-1.0.3.dist-info/top_level.txt
datatang_customer_service-1.0.3.dist-info/RECORD
