Metadata-Version: 2.1
Name: datatang-customer-service
Version: 1.0.3
Summary: This SDK aims to provide customers with a range of features to simplify order management, dataset processing, and data acceptance.
Home-page: UNKNOWN
License: UNKNOWN
Platform: UNKNOWN
Requires-Python: >=3.6
Requires-Dist: loguru >=0.7.2
Requires-Dist: python-dateutil >=2.9.0.post0
Requires-Dist: python-dotenv >=0.21.1
Requires-Dist: requests >=2.31.0
Requires-Dist: azure-core >=1.30.1
Requires-Dist: azure-storage-blob >=12.19.1
Requires-Dist: aliyun-python-sdk-core >=2.15.1
Requires-Dist: aliyun-python-sdk-kms >=2.16.3
Requires-Dist: oss2 >=2.18.6
